Metadata-Version: 1.0
Name: freqlearning
Version: 0.0
Summary: frequency domain learning
Home-page: https://github.com/YaroslavBespalov/freqlearning
Author: YaroslavBespalov, ViktorShipitsin
Author-email: ja.bespalov@yandex.ru
License: UNKNOWN
Platform: UNKNOWN
